toolcode/__init__.py
toolcode/test.py
toolcode/toolcode.py
toolcode-1.1.dist-info/LICENSE
toolcode-1.1.dist-info/METADATA
toolcode-1.1.dist-info/WHEEL
toolcode-1.1.dist-info/top_level.txt
toolcode-1.1.dist-info/RECORD
