Metadata-Version: 2.1
Name: toolcode
Version: 1.1
Summary: is a tool that helps you to perform some functions on facebook , you can read our description
Home-page: https://zalo.me/g/apbppv905
Author: kythai
Author-email: thai thanh ky <kyhacknao@gmail.com>
License: MIT
Project-URL: group, https://zalo.me/g/apbppv905
Project-URL: telegram, https://t.me/+BfXb55fR3sZjNGNl
Classifier: Programming Language :: Python :: 3
Classifier: License :: OSI Approved :: MIT License
Classifier: Operating System :: OS Independent
Requires-Python: >=3.7
License-File: LICENSE
